kc/__init__.py
kc-0.0.6.dist-info/licenses/LICENSE
kc-0.0.6.dist-info/METADATA
kc-0.0.6.dist-info/WHEEL
kc-0.0.6.dist-info/top_level.txt
kc-0.0.6.dist-info/RECORD
