Metadata-Version: 2.4
Name: kc
Version: 0.0.6
Summary: Utils for filtering
Home-page: https://github.com/t-c-w/kc
Author: Thor Whalen
License: apache-2.0
Platform: any
License-File: LICENSE
Dynamic: license-file
